sc_cc_ng_sdk_python/__init__.py
sc_cc_ng_sdk_python-0.3.5.dist-info/METADATA
sc_cc_ng_sdk_python-0.3.5.dist-info/WHEEL
sc_cc_ng_sdk_python-0.3.5.dist-info/RECORD
